dedalus_labs/__init__.py
dedalus_labs/_base_client.py
dedalus_labs/_client.py
dedalus_labs/_compat.py
dedalus_labs/_constants.py
dedalus_labs/_exceptions.py
dedalus_labs/_files.py
dedalus_labs/_models.py
dedalus_labs/_qs.py
dedalus_labs/_resource.py
dedalus_labs/_response.py
dedalus_labs/_streaming.py
dedalus_labs/_types.py
dedalus_labs/_version.py
dedalus_labs/py.typed
dedalus_labs/_utils/__init__.py
dedalus_labs/_utils/_compat.py
dedalus_labs/_utils/_datetime_parse.py
dedalus_labs/_utils/_logs.py
dedalus_labs/_utils/_proxy.py
dedalus_labs/_utils/_reflection.py
dedalus_labs/_utils/_resources_proxy.py
dedalus_labs/_utils/_streams.py
dedalus_labs/_utils/_sync.py
dedalus_labs/_utils/_transform.py
dedalus_labs/_utils/_typing.py
dedalus_labs/_utils/_utils.py
dedalus_labs/lib/.keep
dedalus_labs/lib/_bug_report.py
dedalus_labs/lib/_pydantic.py
dedalus_labs/lib/_tools.py
dedalus_labs/lib/_parsing/__init__.py
dedalus_labs/lib/_parsing/_completions.py
dedalus_labs/lib/runner/__init__.py
dedalus_labs/lib/runner/core.py
dedalus_labs/lib/runner/types/__init__.py
dedalus_labs/lib/runner/types/messages.py
dedalus_labs/lib/runner/types/policy.py
dedalus_labs/lib/runner/types/tools.py
dedalus_labs/lib/streaming/__init__.py
dedalus_labs/lib/streaming/_deltas.py
dedalus_labs/lib/streaming/chat/__init__.py
dedalus_labs/lib/streaming/chat/_completions.py
dedalus_labs/lib/streaming/chat/_events.py
dedalus_labs/lib/streaming/chat/_types.py
dedalus_labs/lib/utils/__init__.py
dedalus_labs/lib/utils/_schemas.py
dedalus_labs/lib/utils/_stream.py
dedalus_labs/resources/__init__.py
dedalus_labs/resources/embeddings.py
dedalus_labs/resources/health.py
dedalus_labs/resources/images.py
dedalus_labs/resources/models.py
dedalus_labs/resources/root.py
dedalus_labs/resources/audio/__init__.py
dedalus_labs/resources/audio/audio.py
dedalus_labs/resources/audio/speech.py
dedalus_labs/resources/audio/transcriptions.py
dedalus_labs/resources/audio/translations.py
dedalus_labs/resources/chat/__init__.py
dedalus_labs-0.1.1.dist-info/METADATA
dedalus_labs-0.1.1.dist-info/WHEEL
dedalus_labs-0.1.1.dist-info/licenses/LICENSE
dedalus_labs-0.1.1.dist-info/RECORD
